air2waterpy/__init__.py
air2waterpy/air2water.py
air2waterpy/air2water_model.py
air2waterpy/gen_params.py
air2waterpy/metrics.py
air2waterpy-0.0.2.dist-info/LICENSE
air2waterpy-0.0.2.dist-info/METADATA
air2waterpy-0.0.2.dist-info/WHEEL
air2waterpy-0.0.2.dist-info/top_level.txt
air2waterpy-0.0.2.dist-info/RECORD
